{
    "schema_version": "1.0.0",
    "name": "ivykis",
    "version": "0.42.4",
    "description": "",
    "comment": "",
    "src": {
        "tarball": {
            "url": "https://sourceforge.net/projects/libivykis/files/0.42.4/ivykis-0.42.4.tar.gz/download"
        }
    },
    "clearingFiles": [
        {
            "fileName": "ivykis-0.42.4.spdx.rdf.xml",
            "priority": "n/a",
            "author": "Oliver Fendt",
            "reviewer": [],
            "alternate_files": [
                {
                    "fileName": "ivykis-0.42.4-SPDX2TV.spdx"
                },
                {
                    "fileName": "ivykis-0.42.4.spdx.json"
                },
                {
                    "fileName": "ivykis-0.42.4.spdx.yaml"
                }
            ]
        }
    ]
}