{
    "schema_version": "1.0.0",
    "name": "which",
    "version": "2.21",
    "description": "",
    "comment": "",
    "src": {
        "tarball": {
            "url": "https://ftp.gnu.org/gnu/which/which-2.21.tar.gz"
        }
    },
    "clearingFiles": [
        {
            "fileName": "which-2.21.spdx.rdf.xml",
            "priority": "n/a",
            "author": "Oliver Fendt",
            "reviewer": [],
            "alternate_files": [
                {
                    "fileName": "which-2.21-SPDX2TV.spdx"
                },
                {
                    "fileName": "which-2.21.spdx.json"
                },
                {
                    "fileName": "which-2.21.spdx.yaml"
                }
            ]
        }
    ]
}