{
    "schema_version": "1.0.0",
    "name": "musl",
    "version": "1.2.3",
    "description": "",
    "comment": "",
    "src": {
        "tarball": {
            "url": "https://musl.libc.org/releases/musl-1.2.3.tar.gz"
        }
    },
    "clearingFiles": [
        {
            "fileName": "musl-1.2.3.spdx.rdf.xml",
            "priority": "n/a",
            "author": "Oliver Fendt",
            "reviewer": [],
            "alternate_files": [
                {
                    "fileName": "musl-1.2.3-SPDX2TV.spdx"
                },
                {
                    "fileName": "musl-1.2.3.spdx.json"
                },
                {
                    "fileName": "musl-1.2.3.spdx.yaml"
                }
            ]
        }
    ]
}