{
    "schema_version": "1.0.0",
    "name": "aom",
    "version": "v3.11.0",
    "description": "",
    "comment": "",
    "src": {
        "tarball": {
            "url": "https://github.com/m-ab-s/aom/archive/refs/tags/v3.11.0.tar.gz"
        }
    },
    "clearingFiles": [
        {
            "fileName": "aom-v3.11.0.spdx.rdf.xml",
            "priority": "n/a",
            "author": "Oliver Fendt",
            "reviewer": [],
            "alternate_files": [
                {
                    "fileName": "aom-v3.11.0-SPDX2TV.spdx"
                },
                {
                    "fileName": "aom-v3.11.0.spdx.json"
                },
                {
                    "fileName": "aom-v3.11.0.spdx.yaml"
                }
            ]
        }
    ]
}