{
    "schema_version": "1.0.0",
    "name": "libgd",
    "version": "2.3.3",
    "description": "",
    "comment": "",
    "src": {
        "tarball": {
            "url": "https://github.com/libgd/libgd/releases/download/gd-2.3.3/libgd-2.3.3.tar.xz"
        }
    },
    "clearingFiles": [
        {
            "fileName": "libgd-2.3.3.spdx.rdf.xml",
            "priority": "n/a",
            "author": "Oliver Fendt",
            "reviewer": [],
            "alternate_files": [
                {
                    "fileName": "libgd-2.3.3-SPDX2TV.spdx"
                },
                {
                    "fileName": "libgd-2.3.3.spdx.json"
                },
                {
                    "fileName": "libgd-2.3.3.spdx.yaml"
                }
            ]
        }
    ]
}