{
    "schema_version": "1.0.0",
    "name": "libexif",
    "version": "libexif-0_6_22-release",
    "description": "",
    "comment": "",
    "src": {
        "tarball": {
            "url": "https://github.com/libexif/libexif/archive/refs/tags/libexif-0_6_22-release.tar.gz"
        }
    },
    "clearingFiles": [
        {
            "fileName": "libexif-libexif-0_6_22-release.spdx.rdf.xml",
            "priority": "n/a",
            "author": "Oliver Fendt",
            "reviewer": [],
            "alternate_files": [
                {
                    "fileName": "libexif-libexif-0_6_22-release-SPDX2TV.spdx"
                },
                {
                    "fileName": "libexif-libexif-0_6_22-release.spdx.json"
                },
                {
                    "fileName": "libexif-libexif-0_6_22-release.spdx.yaml"
                }
            ]
        }
    ]
}