{
    "schema_version": "1.0.0",
    "name": "e2fsprogs",
    "version": "1.47.0",
    "description": "",
    "comment": "The original SPDX tag:value file has 112 MB which is too large to be uploaded, a compressed file is provided.",
    "src": {
        "tarball": {
            "url": "https://mirrors.edge.kernel.org/pub/linux/kernel/people/tytso/e2fsprogs/v1.47.0/e2fsprogs-1.47.0.tar.gz"
        }
    },
    "clearingFiles": [
        {
            "fileName": "",
            "priority": "n/a",
            "author": "Oliver Fendt",
            "reviewer": [],
            "alternate_files": [
                {
                    "fileName": "e2fsprogs-1.47.0-SPDX2TV.spdx.gz"
                },
                {
                    "fileName": "e2fsprogs-1.47.0.spdx.rdf.xml.gz"
                }
            ]
        }
    ]
}