{
    "schema_version": "1.0.0",
    "name": "Chart.js",
    "version": "v4.5.1",
    "description": "",
    "comment": "",
    "src": {
        "tarball": {
            "url": "https://github.com/chartjs/Chart.js/archive/refs/tags/v4.5.1.tar.gz"
        }
    },
    "clearingFiles": [
        {
            "fileName": "Chart.js-v4.5.1.spdx.rdf.xml",
            "priority": "n/a",
            "author": "Oliver Fendt",
            "reviewer": [],
            "alternate_files": [
                {
                    "fileName": "Chart.js-v4.5.1-SPDX2TV.spdx"
                },
                {
                    "fileName": "Chart.js-v4.5.1.spdx.json"
                },
                {
                    "fileName": "Chart.js-v4.5.1.spdx.yaml"
                }
            ]
        }
    ]
}