{
    "schema_version": "1.0.0",
    "name": "attr",
    "version": "2.4.48",
    "description": "",
    "comment": "",
    "src": {
        "tarball": {
            "url": "http://ftp.cc.uoc.gr/mirrors/nongnu.org/attr/attr-2.4.48.tar.gz"
        }
    },
    "clearingFiles": [
        {
            "fileName": "attr-2.4.48.spdx.rdf.xml",
            "priority": "n/a",
            "author": "Oliver Fendt",
            "reviewer": [],
            "alternate_files": [
                {
                    "fileName": "attr-2.4.48-SPDX2TV.spdx"
                },
                {
                    "fileName": "attr-2.4.48.spdx.json"
                },
                {
                    "fileName": "attr-2.4.48.spdx.yaml"
                }
            ]
        }
    ]
}