{
    "schema_version": "1.0.0",
    "name": "libgusb",
    "version": "0.4.8",
    "description": "",
    "comment": "",
    "src": {
        "tarball": {
            "url": "https://github.com/hughsie/libgusb/releases/download/0.4.8/libgusb-0.4.8.tar.xz"
        }
    },
    "clearingFiles": [
        {
            "fileName": "libgusb-0.4.8.spdx.rdf.xml",
            "priority": "n/a",
            "author": "Oliver Fendt",
            "reviewer": [],
            "alternate_files": [
                {
                    "fileName": "libgusb-0.4.8-SPDX2TV.spdx"
                },
                {
                    "fileName": "libgusb-0.4.8.spdx.json"
                },
                {
                    "fileName": "libgusb-0.4.8.spdx.yaml"
                }
            ]
        }
    ]
}