{
    "schema_version": "1.0.0",
    "name": "gzip",
    "version": "1.12",
    "description": "",
    "comment": "",
    "src": {
        "tarball": {
            "url": "https://ftp.gnu.org/gnu/gzip/gzip-1.12.tar.gz"
        }
    },
    "clearingFiles": [
        {
            "fileName": "gzip-1.12.spdx.rdf.xml",
            "priority": "n/a",
            "author": "Oliver Fendt",
            "reviewer": [],
            "alternate_files": [
                {
                    "fileName": "gzip-1.12-SPDX2TV.spdx"
                },
                {
                    "fileName": "gzip-1.12.spdx.json"
                },
                {
                    "fileName": "gzip-1.12.spdx.yaml"
                }
            ]
        }
    ]
}